modbed/__init__.py
modbed/modbed.py
modbed/version.py
modbedtools-0.1.5.data/scripts/modbedtools
modbedtools-0.1.5.dist-info/LICENSE
modbedtools-0.1.5.dist-info/METADATA
modbedtools-0.1.5.dist-info/WHEEL
modbedtools-0.1.5.dist-info/top_level.txt
modbedtools-0.1.5.dist-info/RECORD
