Metadata-Version: 2.1
Name: modbedtools
Version: 0.1.5
Summary: Generate modbed track files for visualization on WashU Epigenome Browser
Home-page: https://github.com/lidaof/modbedtools
Author: Daofeng Li
Author-email: lidaof@gmail.com
Classifier: Programming Language :: Python :: 3
Classifier: License :: OSI Approved :: MIT License
Classifier: Operating System :: OS Independent
License-File: LICENSE
Requires-Dist: pysam
